{
  "machine": "ree-cloud-4",
  "hostname": "ree-cloud-4",
  "last_tick_utc": "2026-05-19T04:58:11Z",
  "state": "running",
  "current_exq": "V3-EXQ-543j",
  "current_exq_started_utc": "2026-05-19T01:56:02.265178+00:00",
  "current_title": "ARC-062 differential-heads cross-machine confirmation of 543i (ree-cloud-4)",
  "current_claim_id": "ARC-062",
  "current_description": "",
  "progress": {
    "run_label": "Seed 2 / ARM_0_baseline",
    "runs_done": 24,
    "runs_total": 36,
    "episodes_done": 40,
    "episodes_total": 108,
    "overall_pct": 67.7
  },
  "seconds_elapsed": 10929,
  "seconds_remaining": 5045,
  "recent_lines": [
    "world_obs_dim=275  agent.gated_policy=off  agent.dacc=off",
    "[train] ARM_0_baseline ep 10/108  phase=P0  rv=0.0003  ep_reward=-1.0032",
    "[train] ARM_0_baseline ep 20/108  phase=P0  rv=0.0004  ep_reward=-0.3984",
    "[train] ARM_0_baseline ep 30/108  phase=P0  rv=0.0006  ep_reward=-1.0627",
    "[train] ARM_0_baseline ep 40/108  phase=P0  rv=0.0006  ep_reward=-1.0087"
  ],
  "queue_depth": null,
  "queue_id_at_head": null,
  "recent_completed": [],
  "runner_pid": 658374,
  "runner_version": null,
  "gpu": {
    "available": false
  },
  "schema_version": "v1"
}
