{
  "machine": "ree-cloud-4",
  "hostname": "ree-cloud-4",
  "last_tick_utc": "2026-05-19T06:30:05Z",
  "state": "running",
  "current_exq": "V3-EXQ-543j",
  "current_exq_started_utc": "2026-05-19T01:56:02.265178+00:00",
  "current_title": "ARC-062 differential-heads cross-machine confirmation of 543i (ree-cloud-4)",
  "current_claim_id": "ARC-062",
  "current_description": "",
  "progress": {
    "run_label": "Seed 2 / ARM_5_dacc_only_xtal",
    "runs_done": 29,
    "runs_total": 36,
    "episodes_done": 80,
    "episodes_total": 108,
    "overall_pct": 82.6
  },
  "seconds_elapsed": 16444,
  "seconds_remaining": 3361,
  "recent_lines": [
    "[train] ARM_5_dacc_only_xtal ep 70/108  phase=P1  rv=0.0005  ep_reward=-1.1343  baseline=-1.0429  buf=0  inert_gating=False",
    "[crystallize] ARM_5_dacc_only_xtal P1 ep 30/60  gated_frozen=0  expansion_params=0  ewc_anchored=True  ewc_active_centers=0  (closure == InfantCurriculumScheduler.on_phase3_entry)",
    "[probe] ARM_5_dacc_only_xtal P1 ep 35/60  applicable=False  mean_tv=0.0000  max_tv=0.0000  buf=0",
    "[probe] ARM_5_dacc_only_xtal P1 ep 40/60  applicable=False  mean_tv=0.0000  max_tv=0.0000  buf=0",
    "[train] ARM_5_dacc_only_xtal ep 80/108  phase=P1  rv=0.0004  ep_reward=-1.0336  baseline=-1.0303  buf=0  inert_gating=False"
  ],
  "queue_depth": null,
  "queue_id_at_head": null,
  "recent_completed": [],
  "runner_pid": 658374,
  "runner_version": null,
  "gpu": {
    "available": false
  },
  "schema_version": "v1"
}
