{
  "machine": "ree-cloud-2",
  "hostname": "ree-cloud-2",
  "last_tick_utc": "2026-05-12T06:22:45Z",
  "state": "running",
  "current_exq": "V3-EXQ-540d",
  "current_exq_started_utc": "2026-05-12T06:18:33.490395+00:00",
  "current_title": "MECH-307 read-site introspection probe (diagnoses V3-EXQ-540b structural conj_fire_rate=0) [re-queue of V3-EXQ-540c killed by 06:10 UTC systemctl restart]",
  "current_claim_id": "MECH-307",
  "current_description": "",
  "progress": {
    "run_label": "Seed 42 / probe_only",
    "runs_done": 0,
    "runs_total": 1,
    "episodes_done": 10,
    "episodes_total": 35,
    "overall_pct": 28.6
  },
  "seconds_elapsed": 252,
  "seconds_remaining": 629,
  "recent_lines": [
    "[v3_exq_540c_mech307_readsite_probe] starting (dry_run=False)",
    "[v3_exq_540c_mech307_readsite_probe] Seed 42 Condition probe_only",
    "[v3_exq_540c_mech307_readsite_probe] warmup=30 eval=5 steps=200 dry_run=False",
    "[train] probe seed=42 ep 5/35 (warmup) contacts=1 bridge_calls=157",
    "[train] probe seed=42 ep 10/35 (warmup) contacts=4 bridge_calls=320"
  ],
  "queue_depth": null,
  "queue_id_at_head": null,
  "recent_completed": [],
  "runner_pid": 2019,
  "runner_version": null,
  "gpu": {
    "available": false
  },
  "schema_version": "v1"
}
