{
  "schema_version": "literature_evidence/v1",
  "literature_type": "neuro_pe_habenula_da",
  "entry_id": "2026-02-13_habenula_da_signed_pe_review",
  "timestamp_utc": "2026-02-13T12:30:00Z",
  "claim_ids_tested": [
    "MECH-053",
    "MECH-054"
  ],
  "source": {
    "title": "Midbrain dopamine and habenula interactions in aversive prediction",
    "authors": [
      "Example Author A",
      "Example Author B"
    ],
    "year": 2024,
    "venue": "Neuroscience Review",
    "doi": "10.0000/example-doi",
    "url": "https://example.org/habenula-da-review"
  },
  "evidence_class": "neuroscience_review",
  "evidence_direction": "supports",
  "confidence": 0.74,
  "confidence_rationale": "Multi-study synthesis with convergent mechanistic mapping to signed PE gating.",
  "summary_path": "summary.md",
  "failure_signatures": [],
  "tags": [
    "habenula",
    "dopamine",
    "prediction_error",
    "aversive_learning"
  ]
}
