{
  "claims_with_stale_entries": [
    {
      "applicable_entries": 6,
      "claim_id": "MECH-060",
      "considered_entries": 48,
      "stale_entries": 42,
      "stale_ratio": 0.875,
      "stale_reasons": {
        "epoch_mismatch": 2,
        "timestamp_before_epoch_start": 40
      }
    },
    {
      "applicable_entries": 2,
      "claim_id": "MECH-058",
      "considered_entries": 37,
      "stale_entries": 35,
      "stale_ratio": 0.946,
      "stale_reasons": {
        "epoch_mismatch": 2,
        "timestamp_before_epoch_start": 33
      }
    },
    {
      "applicable_entries": 6,
      "claim_id": "MECH-059",
      "considered_entries": 32,
      "stale_entries": 26,
      "stale_ratio": 0.812,
      "stale_reasons": {
        "epoch_mismatch": 2,
        "timestamp_before_epoch_start": 24
      }
    },
    {
      "applicable_entries": 6,
      "claim_id": "Q-017",
      "considered_entries": 27,
      "stale_entries": 21,
      "stale_ratio": 0.778,
      "stale_reasons": {
        "timestamp_before_epoch_start": 21
      }
    },
    {
      "applicable_entries": 7,
      "claim_id": "MECH-056",
      "considered_entries": 27,
      "stale_entries": 20,
      "stale_ratio": 0.741,
      "stale_reasons": {
        "epoch_mismatch": 2,
        "timestamp_before_epoch_start": 18
      }
    },
    {
      "applicable_entries": 1,
      "claim_id": "MECH-057",
      "considered_entries": 13,
      "stale_entries": 12,
      "stale_ratio": 0.923,
      "stale_reasons": {
        "epoch_mismatch": 2,
        "timestamp_before_epoch_start": 10
      }
    },
    {
      "applicable_entries": 7,
      "claim_id": "MECH-061",
      "considered_entries": 16,
      "stale_entries": 9,
      "stale_ratio": 0.562,
      "stale_reasons": {
        "epoch_mismatch": 2,
        "timestamp_before_epoch_start": 7
      }
    },
    {
      "applicable_entries": 23,
      "claim_id": "MECH-033",
      "considered_entries": 31,
      "stale_entries": 8,
      "stale_ratio": 0.258,
      "stale_reasons": {
        "timestamp_before_epoch_start": 8
      }
    },
    {
      "applicable_entries": 28,
      "claim_id": "ARC-018",
      "considered_entries": 35,
      "stale_entries": 7,
      "stale_ratio": 0.2,
      "stale_reasons": {
        "timestamp_before_epoch_start": 7
      }
    },
    {
      "applicable_entries": 0,
      "claim_id": "ARC-003",
      "considered_entries": 5,
      "stale_entries": 5,
      "stale_ratio": 1.0,
      "stale_reasons": {
        "timestamp_before_epoch_start": 5
      }
    },
    {
      "applicable_entries": 8,
      "claim_id": "Q-007",
      "considered_entries": 13,
      "stale_entries": 5,
      "stale_ratio": 0.385,
      "stale_reasons": {
        "timestamp_before_epoch_start": 5
      }
    },
    {
      "applicable_entries": 41,
      "claim_id": "ARC-007",
      "considered_entries": 46,
      "stale_entries": 5,
      "stale_ratio": 0.109,
      "stale_reasons": {
        "timestamp_before_epoch_start": 5
      }
    },
    {
      "applicable_entries": 3,
      "claim_id": "Q-006",
      "considered_entries": 7,
      "stale_entries": 4,
      "stale_ratio": 0.571,
      "stale_reasons": {
        "timestamp_before_epoch_start": 4
      }
    },
    {
      "applicable_entries": 4,
      "claim_id": "MECH-026",
      "considered_entries": 8,
      "stale_entries": 4,
      "stale_ratio": 0.5,
      "stale_reasons": {
        "timestamp_before_epoch_start": 4
      }
    },
    {
      "applicable_entries": 4,
      "claim_id": "Q-001",
      "considered_entries": 8,
      "stale_entries": 4,
      "stale_ratio": 0.5,
      "stale_reasons": {
        "timestamp_before_epoch_start": 4
      }
    },
    {
      "applicable_entries": 4,
      "claim_id": "Q-004",
      "considered_entries": 8,
      "stale_entries": 4,
      "stale_ratio": 0.5,
      "stale_reasons": {
        "timestamp_before_epoch_start": 4
      }
    },
    {
      "applicable_entries": 4,
      "claim_id": "Q-005",
      "considered_entries": 8,
      "stale_entries": 4,
      "stale_ratio": 0.5,
      "stale_reasons": {
        "timestamp_before_epoch_start": 4
      }
    },
    {
      "applicable_entries": 5,
      "claim_id": "MECH-029",
      "considered_entries": 9,
      "stale_entries": 4,
      "stale_ratio": 0.444,
      "stale_reasons": {
        "timestamp_before_epoch_start": 4
      }
    },
    {
      "applicable_entries": 5,
      "claim_id": "Q-003",
      "considered_entries": 9,
      "stale_entries": 4,
      "stale_ratio": 0.444,
      "stale_reasons": {
        "timestamp_before_epoch_start": 4
      }
    },
    {
      "applicable_entries": 7,
      "claim_id": "MECH-025",
      "considered_entries": 11,
      "stale_entries": 4,
      "stale_ratio": 0.364,
      "stale_reasons": {
        "timestamp_before_epoch_start": 4
      }
    },
    {
      "applicable_entries": 7,
      "claim_id": "Q-002",
      "considered_entries": 11,
      "stale_entries": 4,
      "stale_ratio": 0.364,
      "stale_reasons": {
        "timestamp_before_epoch_start": 4
      }
    },
    {
      "applicable_entries": 39,
      "claim_id": "ARC-016",
      "considered_entries": 43,
      "stale_entries": 4,
      "stale_ratio": 0.093,
      "stale_reasons": {
        "timestamp_before_epoch_start": 4
      }
    },
    {
      "applicable_entries": 0,
      "claim_id": "ARC-005",
      "considered_entries": 3,
      "stale_entries": 3,
      "stale_ratio": 1.0,
      "stale_reasons": {
        "timestamp_before_epoch_start": 3
      }
    },
    {
      "applicable_entries": 0,
      "claim_id": "MECH-040",
      "considered_entries": 3,
      "stale_entries": 3,
      "stale_ratio": 1.0,
      "stale_reasons": {
        "timestamp_before_epoch_start": 3
      }
    },
    {
      "applicable_entries": 0,
      "claim_id": "MECH-900",
      "considered_entries": 3,
      "stale_entries": 3,
      "stale_ratio": 1.0,
      "stale_reasons": {
        "timestamp_before_epoch_start": 3
      }
    },
    {
      "applicable_entries": 4,
      "claim_id": "MECH-046",
      "considered_entries": 7,
      "stale_entries": 3,
      "stale_ratio": 0.429,
      "stale_reasons": {
        "timestamp_before_epoch_start": 3
      }
    },
    {
      "applicable_entries": 4,
      "claim_id": "Q-012",
      "considered_entries": 7,
      "stale_entries": 3,
      "stale_ratio": 0.429,
      "stale_reasons": {
        "timestamp_before_epoch_start": 3
      }
    },
    {
      "applicable_entries": 4,
      "claim_id": "Q-015",
      "considered_entries": 7,
      "stale_entries": 3,
      "stale_ratio": 0.429,
      "stale_reasons": {
        "timestamp_before_epoch_start": 3
      }
    },
    {
      "applicable_entries": 0,
      "claim_id": "MECH-053",
      "considered_entries": 2,
      "stale_entries": 2,
      "stale_ratio": 1.0,
      "stale_reasons": {
        "timestamp_before_epoch_start": 2
      }
    },
    {
      "applicable_entries": 0,
      "claim_id": "MECH-054",
      "considered_entries": 2,
      "stale_entries": 2,
      "stale_ratio": 1.0,
      "stale_reasons": {
        "timestamp_before_epoch_start": 2
      }
    },
    {
      "applicable_entries": 0,
      "claim_id": "MECH-062",
      "considered_entries": 2,
      "stale_entries": 2,
      "stale_ratio": 1.0,
      "stale_reasons": {
        "timestamp_before_epoch_start": 2
      }
    },
    {
      "applicable_entries": 0,
      "claim_id": "MECH-063",
      "considered_entries": 2,
      "stale_entries": 2,
      "stale_ratio": 1.0,
      "stale_reasons": {
        "timestamp_before_epoch_start": 2
      }
    },
    {
      "applicable_entries": 0,
      "claim_id": "MECH-067",
      "considered_entries": 2,
      "stale_entries": 2,
      "stale_ratio": 1.0,
      "stale_reasons": {
        "epoch_mismatch": 2
      }
    },
    {
      "applicable_entries": 4,
      "claim_id": "Q-016",
      "considered_entries": 6,
      "stale_entries": 2,
      "stale_ratio": 0.333,
      "stale_reasons": {
        "timestamp_before_epoch_start": 2
      }
    },
    {
      "applicable_entries": 0,
      "claim_id": "ARC-001",
      "considered_entries": 1,
      "stale_entries": 1,
      "stale_ratio": 1.0,
      "stale_reasons": {
        "timestamp_before_epoch_start": 1
      }
    },
    {
      "applicable_entries": 0,
      "claim_id": "INV-014",
      "considered_entries": 1,
      "stale_entries": 1,
      "stale_ratio": 1.0,
      "stale_reasons": {
        "timestamp_before_epoch_start": 1
      }
    },
    {
      "applicable_entries": 0,
      "claim_id": "MECH-068",
      "considered_entries": 1,
      "stale_entries": 1,
      "stale_ratio": 1.0,
      "stale_reasons": {
        "timestamp_before_epoch_start": 1
      }
    }
  ],
  "generated_at_utc": "2026-04-29T06:06:28.768427Z",
  "policy": {
    "current_architecture_epoch": "ree_hybrid_guardrails_v1",
    "enabled": true,
    "epoch_start_utc": "2026-02-27T00:00:00Z",
    "require_epoch_tag_for_new_evidence": false,
    "source_types": [
      "*"
    ],
    "stale_if_timestamp_before_epoch_start": true
  },
  "schema_version": "architecture_epoch_applicability/v1",
  "summary": {
    "applicable_entries": 2571,
    "claims_with_stale_entries": 37,
    "considered_entries": 2873,
    "stale_by_reason": {
      "epoch_mismatch": 14,
      "timestamp_before_epoch_start": 288
    },
    "stale_entries": 302
  }
}
