{
  "schema_version": "v1",
  "machine": "ree-cloud-2",
  "commands": [
    {
      "id": "cmd-2026-05-21T13:17:46Z-0da1d0",
      "kind": "resume",
      "args": {},
      "issued_at_utc": "2026-05-21T13:17:46Z",
      "issued_by": "cursor-cloud24-rollout",
      "status": "pending",
      "ack_at_utc": null,
      "completed_at_utc": null,
      "error": null,
      "result_note": null
    },
    {
      "id": "cmd-2026-05-21T12:16:13Z-fca7a1",
      "kind": "pause",
      "args": {},
      "issued_at_utc": "2026-05-21T12:16:13Z",
      "issued_by": "fleet_pause_runners.py",
      "status": "done",
      "ack_at_utc": "2026-05-21T12:19:33Z",
      "completed_at_utc": "2026-05-21T12:19:33Z",
      "error": null,
      "result_note": "paused"
    },
    {
      "id": "cmd-2026-05-21T08:55:53Z-330ce6",
      "kind": "release_claim",
      "args": {
        "queue_id": "V3-EXQ-591"
      },
      "issued_at_utc": "2026-05-21T08:55:53Z",
      "issued_by": "partial-rescue-590a-20260521",
      "status": "done",
      "ack_at_utc": "2026-05-21T09:00:46Z",
      "completed_at_utc": "2026-05-21T09:00:46Z",
      "error": null,
      "result_note": "V3-EXQ-591 claim cleared (was None)"
    },
    {
      "id": "cmd-2026-05-20T07:19:43Z-1a7d0e",
      "kind": "resume",
      "args": {},
      "issued_at_utc": "2026-05-20T07:19:43Z",
      "issued_by": "runner-uptime-20260520T071922Z",
      "status": "done",
      "ack_at_utc": "2026-05-20T19:11:37Z",
      "completed_at_utc": "2026-05-20T19:11:37Z",
      "error": null,
      "result_note": "resumed"
    }
  ]
}
